examplePYPI16/__init__.py
examplePYPI16/area.py
examplePYPI16/factorial.py
examplePYPI16/messages.py
examplePYPI16-0.1.dist-info/LICENSE.txt
examplePYPI16-0.1.dist-info/METADATA
examplePYPI16-0.1.dist-info/WHEEL
examplePYPI16-0.1.dist-info/top_level.txt
examplePYPI16-0.1.dist-info/RECORD
